<annotation>
	<folder>JPEGImages</folder>
	<filename>agya3.jpg</filename>
	<path>D:\Deep Learning Test\anprid\Tensorflow\workspace\images\JPEGImages\agya3.jpg</path>
	<source>
		<database>Unknown</database>
	</source>
	<size>
		<width>860</width>
		<height>645</height>
		<depth>3</depth>
	</size>
	<segmented>0</segmented>
	<object>
		<name>plate</name>
		<pose>Unspecified</pose>
		<truncated>0</truncated>
		<difficult>0</difficult>
		<bndbox>
			<xmin>120</xmin>
			<ymin>382</ymin>
			<xmax>231</xmax>
			<ymax>479</ymax>
		</bndbox>
	</object>
</annotation>
