<annotation>
	<folder>JPEGImages</folder>
	<filename>xpander35.jpg</filename>
	<path>D:\Deep Learning Test\anprid\Tensorflow\workspace\images\JPEGImages\xpander35.jpg</path>
	<source>
		<database>Unknown</database>
	</source>
	<size>
		<width>556</width>
		<height>425</height>
		<depth>3</depth>
	</size>
	<segmented>0</segmented>
	<object>
		<name>plate</name>
		<pose>Unspecified</pose>
		<truncated>0</truncated>
		<difficult>0</difficult>
		<bndbox>
			<xmin>64</xmin>
			<ymin>227</ymin>
			<xmax>115</xmax>
			<ymax>260</ymax>
		</bndbox>
	</object>
</annotation>
